.gitignore
.pylintrc
.readthedocs.yml
CODE_OF_CONDUCT.md
LICENSE
README.rst
requirements.txt
setup.py
.github/workflows/build.yml
.github/workflows/release.yml
adafruit_ble_berrymed_pulse_oximeter/__init__.py
adafruit_ble_berrymed_pulse_oximeter/adafruit_ble_transparent_uart.py
adafruit_circuitpython_ble_pulse_oximeter.egg-info/PKG-INFO
adafruit_circuitpython_ble_pulse_oximeter.egg-info/SOURCES.txt
adafruit_circuitpython_ble_pulse_oximeter.egg-info/dependency_links.txt
adafruit_circuitpython_ble_pulse_oximeter.egg-info/requires.txt
adafruit_circuitpython_ble_pulse_oximeter.egg-info/top_level.txt
docs/api.rst
docs/conf.py
docs/examples.rst
docs/index.rst
docs/_static/favicon.ico
examples/ble_berrymed_pulse_oximeter_simpletest.py