Metadata-Version: 2.1
Name: adafruit-circuitpython-ble-pulse-oximeter
Version: 1.0.1
Summary: BLE Support for BerryMed Pulse Oximeter Service
Home-page: https://github.com/adafruit/Adafruit_CircuitPython_BLE_BerryMed_Pulse_Oximeter
Author: Adafruit Industries
Author-email: circuitpython@adafruit.com
License: MIT
Keywords: adafruit blinka circuitpython micropython ble_contec_pulse_oximeter ble pulse oximeter berrymed spo2
Platform: UNKNOWN
Classifier: Development Status :: 3 - Alpha
Classifier: Intended Audience :: Developers
Classifier: Topic :: Software Development :: Libraries
Classifier: Topic :: System :: Hardware
Classifier: License :: OSI Approved :: MIT License
Classifier: Programming Language :: Python :: 3
Classifier: Programming Language :: Python :: 3.4
Classifier: Programming Language :: Python :: 3.5
